ezi18n/__init__.py
ezi18n/translator.py
ezi18n-1.1.0.dist-info/LICENSE
ezi18n-1.1.0.dist-info/METADATA
ezi18n-1.1.0.dist-info/WHEEL
ezi18n-1.1.0.dist-info/top_level.txt
ezi18n-1.1.0.dist-info/RECORD
