Metadata-Version: 2.1
Name: ezi18n
Version: 1.1.0
Summary: A custom i18n implementation that is built to be easily used.
Author: Pearoo
Author-email: <contact@pearoo.hu>
Keywords: python,i18n,translation,localisation,localization
Classifier: Programming Language :: Python :: 3
Classifier: License :: OSI Approved :: MIT License
Classifier: Operating System :: OS Independent
License-File: LICENSE
